pysyllables/__init__.py
pysyllables/__version__.py
pysyllables/syllable-counts.txt
pysyllables-1.0.3.dist-info/LICENSE
pysyllables-1.0.3.dist-info/METADATA
pysyllables-1.0.3.dist-info/WHEEL
pysyllables-1.0.3.dist-info/top_level.txt
pysyllables-1.0.3.dist-info/RECORD
