Metadata-Version: 2.1
Name: pysyllables
Version: 1.0.3
Summary: An in-memory syllable count dictionary for North American English derived from the CMU Pronouncing Dictionary.
Home-page: https://github.com/voberoi/pysyllables
Author: Vikram Oberoi
Author-email: voberoi@gmail.com
License: MIT
Platform: UNKNOWN
Classifier: License :: OSI Approved :: MIT License
Classifier: Programming Language :: Python
Classifier: Programming Language :: Python :: 3
Classifier: Programming Language :: Python :: 3.6
Classifier: Programming Language :: Python :: Implementation :: CPython
Classifier: Programming Language :: Python :: Implementation :: PyPy
Requires-Python: >=3.6.0
